speechmatics/__init__.py
speechmatics/voice/__init__.py
speechmatics/voice/_audio.py
speechmatics/voice/_client.py
speechmatics/voice/_logging.py
speechmatics/voice/_models.py
speechmatics/voice/_presets.py
speechmatics/voice/_smart_turn.py
speechmatics/voice/_turn.py
speechmatics/voice/_utils.py
speechmatics/voice/_vad.py
speechmatics_voice-0.2.8.dist-info/METADATA
speechmatics_voice-0.2.8.dist-info/WHEEL
speechmatics_voice-0.2.8.dist-info/top_level.txt
speechmatics_voice-0.2.8.dist-info/RECORD
