Metadata-Version: 2.4
Name: speechmatics-voice
Version: 0.2.8
Summary: Speechmatics Voice Agent Python client for Real-Time API
Author-email: Speechmatics <support@speechmatics.com>
License-Expression: MIT
Project-URL: homepage, https://github.com/speechmatics/speechmatics-python-sdk
Project-URL: documentation, https://docs.speechmatics.com/
Project-URL: repository, https://github.com/speechmatics/speechmatics-python-sdk
Project-URL: issues, https://github.com/speechmatics/speechmatics-python-sdk/issues
Keywords: speechmatics,conversational-ai,voice,agents,websocket,real-time,pipecat,livekit
Classifier: Development Status :: 4 - Beta
Classifier: Intended Audience :: Developers
Classifier: Programming Language :: Python :: 3
Classifier: Programming Language :: Python :: 3.9
Classifier: Programming Language :: Python :: 3.10
Classifier: Programming Language :: Python :: 3.11
Classifier: Programming Language :: Python :: 3.12
Classifier: Operating System :: OS Independent
Classifier: Topic :: Multimedia :: Sound/Audio :: Speech
Classifier: Topic :: Software Development :: Libraries :: Python Modules
Requires-Python: >=3.9
Requires-Dist: speechmatics-rt>=0.5.3
Requires-Dist: pydantic<3,>=2.10.6
Requires-Dist: numpy<3,>=1.26.4
Provides-Extra: smart
Requires-Dist: certifi>=2025.10.5; extra == "smart"
Requires-Dist: onnxruntime<2,>=1.20.1; extra == "smart"
Requires-Dist: transformers<5,>=4.57.0; extra == "smart"
Provides-Extra: dev
Requires-Dist: black; extra == "dev"
Requires-Dist: ruff; extra == "dev"
Requires-Dist: mypy; extra == "dev"
Requires-Dist: pre-commit; extra == "dev"
Requires-Dist: pytest; extra == "dev"
Requires-Dist: pytest-asyncio; extra == "dev"
Requires-Dist: pytest-cov; extra == "dev"
Requires-Dist: pytest-mock; extra == "dev"
Requires-Dist: build; extra == "dev"
